corpus_x/__init__.py
corpus_x/__main__.py
corpus_x/codifications.py
corpus_x/documents.py
corpus_x/inclusions.py
corpus_x/resources.py
corpus_x/sql/analysis/missing_dockets_in_opinions.sql
corpus_x/sql/analysis/missing_phil_in_opinions.sql
corpus_x/sql/analysis/missing_scra_in_opinions.sql
corpus_x/sql/base/get_author_ids.sql
corpus_x/sql/base/get_detail.sql
corpus_x/sql/codes/events/search_unmaterialized.sql
corpus_x/sql/codes/events/set_decision_id.sql
corpus_x/sql/codes/events/set_statute_id.sql
corpus_x/sql/codes/events/set_statute_unit_mp.sql
corpus_x/sql/codes/get_base.sql
corpus_x/sql/codes/list_event_statutes.sql
corpus_x/sql/codes/list_unique_statute_category_idxes_from_events.sql
corpus_x/sql/codes/update_statute_id.sql
corpus_x/sql/decisions/get_base.sql
corpus_x/sql/decisions/inclusions/popular_citations.sql
corpus_x/sql/decisions/inclusions/popular_statutes.sql
corpus_x/sql/decisions/inclusions/read_opinions.sql
corpus_x/sql/decisions/inclusions/update_decision_id.sql
corpus_x/sql/decisions/list_opinions_of_decision.sql
corpus_x/sql/statutes/get_base.sql
corpus_x/sql/statutes/list_affected_statutes.sql
corpus_x/sql/statutes/list_affector_statutes.sql
corpus_x/sql/statutes/references/src_ref_mp_list.sql
corpus_x/sql/statutes/references/unique_statutes_list.sql
corpus_x/sql/statutes/update_id.sql
corpus_x/statutes.py
corpus_x/utils/__init__.py
corpus_x/utils/_loggers.py
corpus_x/utils/history.py
corpus_x-0.0.2.dist-info/WHEEL
corpus_x-0.0.2.dist-info/METADATA
corpus_x-0.0.2.dist-info/RECORD
