Metadata-Version: 2.1
Name: corpus-x
Version: 0.0.2
Summary: Add codification and statute tables to pre-existing corpus-base database.
Home-page: https://lawsql.com
Author: Marcelino G. Veloso III
Author-email: mars@veloso.one
Requires-Python: >=3.11,<4.0
Classifier: Development Status :: 4 - Beta
Classifier: Framework :: Pydantic
Classifier: Framework :: Pytest
Classifier: Intended Audience :: Legal Industry
Classifier: Programming Language :: Python :: 3
Classifier: Programming Language :: Python :: 3.11
Classifier: Programming Language :: Python :: 3.11
Classifier: Typing :: Typed
Requires-Dist: corpus-base (>=0.1.10,<0.2.0)
Requires-Dist: statute-trees (>=0.1.0,<0.2.0)
Project-URL: Documentation, https://justmars.github.io/corpus-x
Project-URL: Repository, https://github.com/justmars/corpus-x
